yabi/__init__.py
yabi/blog.py
yabi/command_line.py
yabi/post.py
yabi/data/style_sheets/style.css
yabi/templates/all_archive.html
yabi/templates/all_tags.html
yabi/templates/archive.html
yabi/templates/base.html
yabi/templates/index.html
yabi/templates/post.html
yabi/templates/tag.html
yabi-1.0.dist-info/LICENSE
yabi-1.0.dist-info/METADATA
yabi-1.0.dist-info/WHEEL
yabi-1.0.dist-info/entry_points.txt
yabi-1.0.dist-info/top_level.txt
yabi-1.0.dist-info/RECORD
