Metadata-Version: 2.1
Name: yabi
Version: 1.0
Summary: A static blog generator
Home-page: https://github.com/menganha/yabi
Author: menganha
License: BSD 2-Clause License
Keywords: blog,web
Requires-Python: >=3.10
License-File: LICENSE
Requires-Dist: jinja2
Requires-Dist: markdown
